easyidp/__init__.py
easyidp/cvtools.py
easyidp/data.py
easyidp/geotiff.py
easyidp/geotools.py
easyidp/jsonfile.py
easyidp/metashape.py
easyidp/pix4d.py
easyidp/pointcloud.py
easyidp/py.typed
easyidp/reconstruct.py
easyidp/roi.py
easyidp/shp.py
easyidp/visualize.py
easyidp-2.0.1.dist-info/METADATA
easyidp-2.0.1.dist-info/WHEEL
easyidp-2.0.1.dist-info/RECORD
