Metadata-Version: 2.4
Name: easyidp
Version: 2.0.1
Summary: A handy tool for dealing with region of interest (ROI) on the image reconstruction (Metashape & Pix4D) outputs, mainly in agriculture applications
Project-URL: documentation, https://easyidp.readthedocs.io/en/latest/
Project-URL: source, https://github.com/UTokyo-FieldPhenomics-Lab/EasyIDP
Project-URL: issues, https://github.com/UTokyo-FieldPhenomics-Lab/EasyIDP/issues
Project-URL: forum, https://github.com/UTokyo-FieldPhenomics-Lab/EasyIDP/discussions
Author-email: Haozhou Wang <howcanoewang@gmail.com>
License: MIT
Classifier: Development Status :: 4 - Beta
Classifier: Intended Audience :: Science/Research
Classifier: Operating System :: OS Independent
Classifier: Programming Language :: Python :: 3
Classifier: Programming Language :: Python :: 3 :: Only
Classifier: Programming Language :: Python :: 3.10
Classifier: Programming Language :: Python :: 3.11
Classifier: Programming Language :: Python :: 3.12
Classifier: Programming Language :: Python :: 3.13
Classifier: Topic :: Scientific/Engineering :: GIS
Requires-Python: >=3.10
Requires-Dist: chardet>=5.2.0
Requires-Dist: gdown>=5.2.0
Requires-Dist: geojson>=3.2.0
Requires-Dist: imagecodecs>=2025.3.30
Requires-Dist: laspy>=2.5.4
Requires-Dist: lazrs>=0.6.3
Requires-Dist: matplotlib>=3.10.3
Requires-Dist: numpy>=2.2.5
Requires-Dist: plyfile>=1.1
Requires-Dist: pyproj>=3.7.1
Requires-Dist: pyshp>=2.3.1
Requires-Dist: scikit-image>=0.25.2
Requires-Dist: shapely>=2.1.0
Requires-Dist: tabulate>=0.9.0
Requires-Dist: tifffile>=2025.5.10
Requires-Dist: tqdm>=4.67.1
